libname/__init__.py
libname/kookoo.py
kookoo-0.0.1.dist-info/METADATA
kookoo-0.0.1.dist-info/WHEEL
kookoo-0.0.1.dist-info/top_level.txt
kookoo-0.0.1.dist-info/RECORD
