Metadata-Version: 2.1
Name: kookoo
Version: 0.0.1
Summary: Test pakket neef
Author: real badman)
Author-email: <real@badman.com>
Keywords: koo,koo
Classifier: Development Status :: 1 - Planning
Classifier: Intended Audience :: Developers
Classifier: Programming Language :: Python :: 3
Classifier: Operating System :: Unix
Classifier: Operating System :: MacOS :: MacOS X
Classifier: Operating System :: Microsoft :: Windows
